PySquashfsImage/__init__.py
PySquashfsImage/__main__.py
PySquashfsImage/compressor.py
PySquashfsImage/const.py
PySquashfsImage/extract.py
PySquashfsImage/file.py
PySquashfsImage/macro.py
PySquashfsImage/util.py
PySquashfsImage/xattr.py
PySquashfsImage/structure/__init__.py
PySquashfsImage/structure/inode.py
PySquashfsImage-0.9.0.dist-info/LICENSE.GPL3
PySquashfsImage-0.9.0.dist-info/LICENSE.LGPL
PySquashfsImage-0.9.0.dist-info/METADATA
PySquashfsImage-0.9.0.dist-info/WHEEL
PySquashfsImage-0.9.0.dist-info/entry_points.txt
PySquashfsImage-0.9.0.dist-info/top_level.txt
PySquashfsImage-0.9.0.dist-info/RECORD
